magicdict/__init__.py
magicdict/_dict.py
magicdict/_frozen_dict.py
magicdict/_frozen_tolerant_dict.py
magicdict/_items_view.py
magicdict/_keys_view.py
magicdict/_tolerant_dict.py
magicdict/_values_view.py
magicdict/_version.py
magicdict/py.typed
magicdict-1.0.6.dist-info/LICENSE
magicdict-1.0.6.dist-info/METADATA
magicdict-1.0.6.dist-info/WHEEL
magicdict-1.0.6.dist-info/top_level.txt
magicdict-1.0.6.dist-info/RECORD
