Metadata-Version: 2.1
Name: magicdict
Version: 1.0.6
Summary: An ordered, one-to-many mapping.
Home-page: https://github.com/futursolo/magicdict
Author: Kaede Hoshikawa
Author-email: futursolo@icloud.com
License: Apache License 2.0
Platform: UNKNOWN
Classifier: Operating System :: MacOS
Classifier: Operating System :: MacOS :: MacOS X
Classifier: Operating System :: Microsoft
Classifier: Operating System :: Microsoft :: Windows
Classifier: Operating System :: POSIX
Classifier: Operating System :: POSIX :: Linux
Classifier: Operating System :: Unix
Classifier: Programming Language :: Python
Classifier: Programming Language :: Python :: 3 :: Only
Requires-Python: >=3.6.0
Requires-Dist: importlib-metadata (>=1.7.0) ; python_version < "3.8"
Provides-Extra: test
Requires-Dist: pytest (<7,>=6.0.1) ; extra == 'test'
Requires-Dist: pytest-benchmark (<4,>=3.2.3) ; extra == 'test'
Requires-Dist: flake8 (<4,>=3.8.2) ; extra == 'test'
Requires-Dist: mypy (<1,>=0.782) ; extra == 'test'
